mouse_tracker/__init__.py
mouse_tracker/tracker.py
mouse_tracker/weights/best.pt
mus_musculus_tracker-0.1.3.dist-info/licenses/LICENSE
mus_musculus_tracker-0.1.3.dist-info/METADATA
mus_musculus_tracker-0.1.3.dist-info/WHEEL
mus_musculus_tracker-0.1.3.dist-info/entry_points.txt
mus_musculus_tracker-0.1.3.dist-info/top_level.txt
mus_musculus_tracker-0.1.3.dist-info/RECORD
